content_tools/__init__.py
content_tools/__main__.py
content_tools/json_schemas.py
dw_content_tools-0.8.1.dist-info/entry_points.txt
dw_content_tools-0.8.1.dist-info/WHEEL
dw_content_tools-0.8.1.dist-info/METADATA
dw_content_tools-0.8.1.dist-info/RECORD
