Metadata-Version: 2.1
Name: dw-content-tools
Version: 0.8.1
Summary: 
Author: Martin Zugnoni
Author-email: mzugnoni@datawars.io
Requires-Python: >=3.8,<4.0
Classifier: Programming Language :: Python :: 3
Classifier: Programming Language :: Python :: 3.8
Classifier: Programming Language :: Python :: 3.9
Classifier: Programming Language :: Python :: 3.10
Classifier: Programming Language :: Python :: 3.11
Requires-Dist: beautifulsoup4 (>=4.11.1,<5.0.0)
Requires-Dist: click (>=8.1.3,<9.0.0)
Requires-Dist: jsonschema (>=4.17.3,<5.0.0)
Requires-Dist: pyyaml (>=6.0,<7.0)
